.gitignore
Changes.rst
LICENSE
Makefile
README.rst
common.mk
setup.cfg
setup.py
docs/conf.py
docs/index.rst
preset_sqlalchemy_aurora_data_api.egg-info/PKG-INFO
preset_sqlalchemy_aurora_data_api.egg-info/SOURCES.txt
preset_sqlalchemy_aurora_data_api.egg-info/dependency_links.txt
preset_sqlalchemy_aurora_data_api.egg-info/entry_points.txt
preset_sqlalchemy_aurora_data_api.egg-info/requires.txt
preset_sqlalchemy_aurora_data_api.egg-info/top_level.txt
sqlalchemy_aurora_data_api/__init__.py
test/test.py