Metadata-Version: 1.1
Name: preset-sqlalchemy-aurora-data-api
Version: 0.2.8
Summary: An AWS Aurora Serverless Data API dialect for SQLAlchemy. This is a temporary package that allows credentials to be passed via the SQLAlchemy URI.
Home-page: https://github.com/preset-io/sqlalchemy-aurora-data-api
Author: Andrey Kislyuk
Author-email: akislyuk@chanzuckerberg.com
License: Apache Software License
Platform: MacOS X
Platform: Posix
Classifier: Intended Audience :: Developers
Classifier: License :: OSI Approved :: Apache Software License
Classifier: Operating System :: MacOS :: MacOS X
Classifier: Operating System :: POSIX
Classifier: Programming Language :: Python
Classifier: Programming Language :: Python :: 3.5
Classifier: Programming Language :: Python :: 3.6
Classifier: Programming Language :: Python :: 3.7
Classifier: Programming Language :: Python :: 3.8
Classifier: Topic :: Software Development :: Libraries :: Python Modules
